conan_convenience/__init__.py
conan_convenience/cConvenience.py
conan_convenience/config.py
conan_convenience/helper/__init__.py
conan_convenience/helper/conan_cmd_generator.py
conan_convenience/helper/downloader/__init__.py
conan_convenience/helper/downloader/downloader.py
conan_convenience/helper/downloader/gitlab.py
conan_convenience/helper/downloader/http.py
conan_convenience/helper/downloader/local.py
conan_convenience/helper/git.py
conan_convenience/helper/profile_parsers.py
conan_convenience/helper/project_helper.py
conan_convenience/helper/tools.py
conan_convenience/helper/version.py
conan_convenience/ui.py
conan_convenience-0.1.0.dist-info/entry_points.txt
conan_convenience-0.1.0.dist-info/METADATA
conan_convenience-0.1.0.dist-info/WHEEL
conan_convenience-0.1.0.dist-info/RECORD
