Metadata-Version: 2.1
Name: conan-convenience
Version: 0.1.0
Summary: A little convenience script, which should make your life with conan, pre-commit and clan-format easier.
Author: Philip Ecker
Author-email: eph
Requires-Python: >=3.11,<4.0
Classifier: Programming Language :: Python :: 3
Classifier: Programming Language :: Python :: 3.11
Requires-Dist: clang-format (>=16.0.6,<17.0.0)
Requires-Dist: confuse (>=2.0.1,<3.0.0)
Requires-Dist: cpplint (>=1.6.1,<2.0.0)
Requires-Dist: gitignore-parser (>=0.1.6,<0.2.0)
Requires-Dist: pre-commit (>=3.3.3,<4.0.0)
Requires-Dist: pygit2 (>=1.12.2,<2.0.0)
Requires-Dist: pymarkdownlnt (>=0.9.12,<0.10.0)
Requires-Dist: python-gitlab (>=3.15.0,<4.0.0)
Requires-Dist: requests (>=2.31.0,<3.0.0)
